MJallTest/__init__.py
MJallTest-0.1.dist-info/LICENSE
MJallTest-0.1.dist-info/METADATA
MJallTest-0.1.dist-info/WHEEL
MJallTest-0.1.dist-info/top_level.txt
MJallTest-0.1.dist-info/RECORD
