Metadata-Version: 2.1
Name: MJallTest
Version: 0.1
Summary: Testing all
Home-page: UNKNOWN
Author: JagrithiMudike
Author-email: jmudike@mail.bradley.edu
License: UNKNOWN
Platform: UNKNOWN
Classifier: Programming Language :: Python :: 3.10
Classifier: License :: OSI Approved :: MIT License
Classifier: Operating System :: OS Independent
License-File: LICENSE
